Metadata-Version: 2.1
Name: lucy-spc
Version: 0.0.1
Summary: A Python library for reading and writing .spc files
Home-page: https://github.com/aswin-kevin/lucy-spc
Author: Aswin Venkat
Author-email: aswinvenkat60@gmail.com
License: MIT
Keywords: spc
Platform: UNKNOWN
Classifier: Development Status :: 3 - Alpha
Classifier: Intended Audience :: Developers
Classifier: License :: OSI Approved :: MIT License
Classifier: Programming Language :: Python :: 3
Classifier: Programming Language :: Python :: 3.6
Classifier: Programming Language :: Python :: 3.7
Classifier: Programming Language :: Python :: 3.8
Classifier: Programming Language :: Python :: 3.9
